casaconfig/__init__.py
casaconfig/__main__.py
casaconfig/config.py
casaconfig/private/CasaconfigErrors.py
casaconfig/private/__init__.py
casaconfig/private/casasiteconfig_example.py
casaconfig/private/config_defaults.py
casaconfig/private/config_defaults_static.py
casaconfig/private/data_available.py
casaconfig/private/data_update.py
casaconfig/private/do_auto_updates.py
casaconfig/private/do_pull_data.py
casaconfig/private/do_untar_url.py
casaconfig/private/get_argparser.py
casaconfig/private/get_available_files.py
casaconfig/private/get_config.py
casaconfig/private/get_data_info.py
casaconfig/private/get_data_lock.py
casaconfig/private/have_network.py
casaconfig/private/io_redirect.py
casaconfig/private/measures_available.py
casaconfig/private/measures_update.py
casaconfig/private/print_log_messages.py
casaconfig/private/pull_data.py
casaconfig/private/read_readme.py
casaconfig/private/set_casacore_path.py
casaconfig/private/summary.py
casaconfig/private/update_all.py
casaconfig-1.4.0.dist-info/licenses/LICENSE
tests/test_casaconfig.py
casaconfig-1.4.0.dist-info/METADATA
casaconfig-1.4.0.dist-info/WHEEL
casaconfig-1.4.0.dist-info/top_level.txt
casaconfig-1.4.0.dist-info/RECORD
