Metadata-Version: 2.4
Name: casaconfig
Version: 1.4.0
Summary: CASA Operational Configuration Package
Author-email: National Radio Astronomy Observatory <casa-feedback@nrao.edu>
License-Expression: Apache-2.0
Project-URL: Homepage, https://casa.nrao.edu/
Project-URL: Documentation, https://casadocs.readthedocs.io/
Project-URL: Repository, https://github.com/casangi/casaconfig.git
Requires-Python: >=3.10
License-File: LICENSE
Requires-Dist: certifi>=2023.5.7
Dynamic: license-file
